[
    {
        "key": "dbln",
        "value": "%7B%2261572856146526%22%3A%22c7YegZHs%22%2C%2261570071321609%22%3A%221XL6IR5T%22%7D",
        "domain": "facebook.com",
        "path": "/login/device-based/",
        "hostOnly": false,
        "creation": "2025-02-21T03:53:04.349Z",
        "lastAccessed": "2025-02-21T03:53:04.350Z"
    },
    {
        "key": "datr",
        "value": "nbaUZynJWk8z_dsPEp5ZAF1Y",
        "domain": "facebook.com",
        "path": "/",
        "hostOnly": false,
        "creation": "2025-02-21T03:53:04.350Z",
        "lastAccessed": "2025-02-21T03:53:04.350Z"
    },
    {
        "key": "sb",
        "value": "nbaUZ5wVeZu2QRpi_sYlxlu7",
        "domain": "facebook.com",
        "path": "/",
        "hostOnly": false,
        "creation": "2025-02-21T03:53:04.350Z",
        "lastAccessed": "2025-02-21T03:53:04.350Z"
    },
    {
        "key": "ps_l",
        "value": "1",
        "domain": "facebook.com",
        "path": "/",
        "hostOnly": false,
        "creation": "2025-02-21T03:53:04.350Z",
        "lastAccessed": "2025-02-21T03:53:04.350Z"
    },
    {
        "key": "ps_n",
        "value": "1",
        "domain": "facebook.com",
        "path": "/",
        "hostOnly": false,
        "creation": "2025-02-21T03:53:04.350Z",
        "lastAccessed": "2025-02-21T03:53:04.350Z"
    },
    {
        "key": "vpd",
        "value": "v1%3B537x314x3.43505597114563",
        "domain": "facebook.com",
        "path": "/",
        "hostOnly": false,
        "creation": "2025-02-21T03:53:04.350Z",
        "lastAccessed": "2025-02-21T03:53:04.350Z"
    },
    {
        "key": "wd",
        "value": "315x537",
        "domain": "facebook.com",
        "path": "/",
        "hostOnly": false,
        "creation": "2025-02-21T03:53:04.350Z",
        "lastAccessed": "2025-02-21T03:53:04.350Z"
    },
    {
        "key": "c_user",
        "value": "61559715091297",
        "domain": "facebook.com",
        "path": "/",
        "hostOnly": false,
        "creation": "2025-02-21T03:53:04.350Z",
        "lastAccessed": "2025-02-21T03:53:04.350Z"
    },
    {
        "key": "fr",
        "value": "0Xay1D3CYulhb6Jr2.AWUPvEgRGN2tjMP9iZJ0UzINHvmP_FSmmU7A0Q.BnlLad..AAA.0.0.BntZnM.AWWNiuemeW0",
        "domain": "facebook.com",
        "path": "/",
        "hostOnly": false,
        "creation": "2025-02-21T03:53:04.350Z",
        "lastAccessed": "2025-02-21T03:53:04.350Z"
    },
    {
        "key": "xs",
        "value": "1%3Ay8_EMwr8cJQfdQ%3A2%3A1739954637%3A-1%3A14754",
        "domain": "facebook.com",
        "path": "/",
        "hostOnly": false,
        "creation": "2025-02-21T03:53:04.350Z",
        "lastAccessed": "2025-02-21T03:53:04.351Z"
    },
    {
        "key": "locale",
        "value": "en_GB",
        "domain": "facebook.com",
        "path": "/",
        "hostOnly": false,
        "creation": "2025-02-21T03:53:04.351Z",
        "lastAccessed": "2025-02-21T03:53:04.351Z"
    },
    {
        "key": "fbl_st",
        "value": "101536951%3BT%3A29001832",
        "domain": "facebook.com",
        "path": "/",
        "hostOnly": false,
        "creation": "2025-02-21T03:53:04.351Z",
        "lastAccessed": "2025-02-21T03:53:04.351Z"
    },
    {
        "key": "wl_cbv",
        "value": "v2%3Bclient_version%3A2746%3Btimestamp%3A1740109976",
        "domain": "facebook.com",
        "path": "/",
        "hostOnly": false,
        "creation": "2025-02-21T03:53:04.351Z",
        "lastAccessed": "2025-02-21T03:53:04.351Z"
    }
]
