[
    {
        "key": "dbln",
        "value": "%7B%2261572856146526%22%3A%225sYCeUWR%22%2C%2261570071321609%22%3A%22XcTHZYxV%22%2C%2261559715091297%22%3A%22PdUy3Pw5%22%7D",
        "domain": "facebook.com",
        "path": "/login/device-based/",
        "hostOnly": false,
        "creation": "2025-02-25T01:32:53.026Z",
        "lastAccessed": "2025-02-25T01:32:53.028Z"
    },
    {
        "key": "datr",
        "value": "nbaUZynJWk8z_dsPEp5ZAF1Y",
        "domain": "facebook.com",
        "path": "/",
        "hostOnly": false,
        "creation": "2025-02-25T01:32:53.028Z",
        "lastAccessed": "2025-02-25T01:32:53.028Z"
    },
    {
        "key": "sb",
        "value": "nbaUZ5wVeZu2QRpi_sYlxlu7",
        "domain": "facebook.com",
        "path": "/",
        "hostOnly": false,
        "creation": "2025-02-25T01:32:53.028Z",
        "lastAccessed": "2025-02-25T01:32:53.028Z"
    },
    {
        "key": "ps_l",
        "value": "1",
        "domain": "facebook.com",
        "path": "/",
        "hostOnly": false,
        "creation": "2025-02-25T01:32:53.028Z",
        "lastAccessed": "2025-02-25T01:32:53.028Z"
    },
    {
        "key": "ps_n",
        "value": "1",
        "domain": "facebook.com",
        "path": "/",
        "hostOnly": false,
        "creation": "2025-02-25T01:32:53.028Z",
        "lastAccessed": "2025-02-25T01:32:53.028Z"
    },
    {
        "key": "vpd",
        "value": "v1%3B537x314x3.43505597114563",
        "domain": "facebook.com",
        "path": "/",
        "hostOnly": false,
        "creation": "2025-02-25T01:32:53.028Z",
        "lastAccessed": "2025-02-25T01:32:53.028Z"
    },
    {
        "key": "locale",
        "value": "en_GB",
        "domain": "facebook.com",
        "path": "/",
        "hostOnly": false,
        "creation": "2025-02-25T01:32:53.028Z",
        "lastAccessed": "2025-02-25T01:32:53.028Z"
    },
    {
        "key": "m_pixel_ratio",
        "value": "3.43505597114563",
        "domain": "facebook.com",
        "path": "/",
        "hostOnly": false,
        "creation": "2025-02-25T01:32:53.028Z",
        "lastAccessed": "2025-02-25T01:32:53.028Z"
    },
    {
        "key": "x-referer",
        "value": "eyJyIjoiL2NoZWNrcG9pbnQvMTUwMTA5MjgyMzUyNTI4Mi9sb2dvdXQvP25leHQ9aHR0cHMlM0ElMkYlMkZtLmZhY2Vib29rLmNvbSUyRiIsImgiOiIvY2hlY2twb2ludC8xNTAxMDkyODIzNTI1MjgyL2xvZ291dC8%2FbmV4dD1odHRwcyUzQSUyRiUyRm0uZmFjZWJvb2suY29tJTJGIiwicyI6Im0ifQ%3D%3D",
        "domain": "facebook.com",
        "path": "/",
        "hostOnly": false,
        "creation": "2025-02-25T01:32:53.028Z",
        "lastAccessed": "2025-02-25T01:32:53.028Z"
    },
    {
        "key": "wd",
        "value": "315x537",
        "domain": "facebook.com",
        "path": "/",
        "hostOnly": false,
        "creation": "2025-02-25T01:32:53.028Z",
        "lastAccessed": "2025-02-25T01:32:53.028Z"
    },
    {
        "key": "c_user",
        "value": "61559715091297",
        "domain": "facebook.com",
        "path": "/",
        "hostOnly": false,
        "creation": "2025-02-25T01:32:53.028Z",
        "lastAccessed": "2025-02-25T01:32:53.028Z"
    },
    {
        "key": "fr",
        "value": "0Xay1D3CYulhb6Jr2.AWXILngr3w1EIzT3lOLNsfhhHGHaq00rkVRsUQ.BnlLad..AAA.0.0.BnvR2x.AWU2o2lZaQE",
        "domain": "facebook.com",
        "path": "/",
        "hostOnly": false,
        "creation": "2025-02-25T01:32:53.028Z",
        "lastAccessed": "2025-02-25T01:32:53.028Z"
    },
    {
        "key": "xs",
        "value": "3%3AgBJhzS_uNuBQJA%3A2%3A1740447153%3A-1%3A14754",
        "domain": "facebook.com",
        "path": "/",
        "hostOnly": false,
        "creation": "2025-02-25T01:32:53.028Z",
        "lastAccessed": "2025-02-25T01:32:53.028Z"
    },
    {
        "key": "fbl_st",
        "value": "100420207%3BT%3A29007452",
        "domain": "facebook.com",
        "path": "/",
        "hostOnly": false,
        "creation": "2025-02-25T01:32:53.028Z",
        "lastAccessed": "2025-02-25T01:32:53.028Z"
    },
    {
        "key": "wl_cbv",
        "value": "v2%3Bclient_version%3A2749%3Btimestamp%3A1740447156",
        "domain": "facebook.com",
        "path": "/",
        "hostOnly": false,
        "creation": "2025-02-25T01:32:53.028Z",
        "lastAccessed": "2025-02-25T01:32:53.028Z"
    }
]
